postreal/__init__.py
postreal/definitions.py
postreal/postreal.py
postreal/cli/__init__.py
postreal/cli/config.py
postreal/cli/inventory.py
postreal/cli/main.py
postreal/cli/publish.py
postreal/cli/script.py
postreal/cli/setup.py
postreal/cli/surreal.py
postreal/cli/sync.py
postreal/cli/task.py
postreal/cli/wingdbstub.py
postreal/cli/workspace.py
postreal/helpers/__init__.py
postreal/helpers/faker.py
postreal/helpers/general.py
postreal/helpers/loaders.py
postreal/helpers/models.py
postreal/helpers/surreal.py
postreal/logic/__init__.py
postreal/logic/crawler.py
postreal/logic/inventory.py
postreal/logic/postreal.py
postreal/mappers/__init__.py
postreal/mappers/inventory.py
postreal/models/__init__.py
postreal/models/base.py
postreal/models/config.py
postreal/models/enums.py
postreal/models/inventory.py
postreal/models/postreal.py
postreal/models/script.py
postreal/models/task.py
postreal/ports/__init__.py
postreal/ports/preferences.py
postreal/storage/__init__.py
postreal/storage/surreal.py
postreal-0.1.0.dist-info/AUTHORS.rst
postreal-0.1.0.dist-info/LICENSE
postreal-0.1.0.dist-info/METADATA
postreal-0.1.0.dist-info/WHEEL
postreal-0.1.0.dist-info/entry_points.txt
postreal-0.1.0.dist-info/top_level.txt
postreal-0.1.0.dist-info/RECORD
